Workbook

Sheet 资产负债表
B1: 资产负债表（适用执行小企业会计准则的企业）
I2: 会小企01表 单位：元
B3: 纳税人识别号 | F3: 纳税人名称
B4: 所属期起 | F4: 所属期止
B5: 资产 | C5: 行次 | D5: 期末余额 | E5: 年初余额 | F5: 负债和所有者权益 | G5: 行次 | H5: 期末余额 | I5: 年初余额
B6: 流动资产： | F6: 流动负债：
B7: 货币资金 | C7: 1 | D7: 0 | E7: 0 | F7: 短期借款 | G7: 31 | H7: 0 | I7: 0
B8: 短期投资 | C8: 2 | D8: 0 | E8: 0 | F8: 应付票据 | G8: 32 | H8: 0 | I8: 0
B9: 应收票据 | C9: 3 | D9: 0 | E9: 0 | F9: 应付账款 | G9: 33 | H9: 0 | I9: 0
B10: 应收账款 | C10: 4 | D10: 0 | E10: 0 | F10: 预收账款 | G10: 34 | H10: 0 | I10: 0
B11: 预付账款 | C11: 5 | D11: 0 | E11: 0 | F11: 应付职工薪酬 | G11: 35 | H11: 0 | I11: 0
B12: 应收股利 | C12: 6 | D12: 0 | E12: 0 | F12: 应交税费 | G12: 36 | H12: 0 | I12: 0
B13: 应收利息 | C13: 7 | D13: 0 | E13: 0 | F13: 应付利息 | G13: 37 | H13: 0 | I13: 0
B14: 其他应收款 | C14: 8 | D14: 0 | E14: 0 | F14: 应付利润 | G14: 38 | H14: 0 | I14: 0
B15: 存货 | C15: 9 | D15: 0 | E15: 0 | F15: 其他应付款 | G15: 39 | H15: 0 | I15: 0
B16: 其中：原材料 | C16: 10 | D16: 0 | E16: 0 | F16: 其他流动负债 | G16: 40 | H16: 0 | I16: 0
B17: 在产品 | C17: 11 | D17: 0 | E17: 0 | F17: 流动负债合计 | G17: 41 | H17: =ROUND(H7+H8+H9+H10+H11+H12+H13+H14+H15+H16,2) -> 0 | I17: =ROUND(I7+I8+I9+I10+I11+I12+I13+I14+I15+I16,2) -> 0
B18: 库存商品 | C18: 12 | D18: 0 | E18: 0 | F18: 非流动负债：
B19: 周转材料 | C19: 13 | D19: 0 | E19: 0 | F19: 长期借款 | G19: 42 | H19: 0 | I19: 0
B20: 其他流动资产 | C20: 14 | D20: 0 | E20: 0 | F20: 长期应付款 | G20: 43 | H20: 0 | I20: 0
B21: 流动资产合计 | C21: 15 | D21: =ROUND(D7+D8+D9+D10+D11+D12+D13+D14+D15+D20,2) -> 0 | E21: =ROUND(E7+E8+E9+E10+E11+E12+E13+E14+E15+E20,2) -> 0 | F21: 递延收益 | G21: 44 | H21: 0 | I21: 0
B22: 非流动资产： | F22: 其他非流动负债 | G22: 45 | H22: 0 | I22: 0
B23: 长期债券投资 | C23: 16 | D23: 0 | E23: 0 | F23: 非流动负债合计 | G23: 46 | H23: =ROUND(H19+H20+H21+H22,2) -> 0 | I23: =ROUND(I19+I20+I21+I22,2) -> 0
B24: 长期股权投资 | C24: 17 | D24: 0 | E24: 0 | F24: 负债合计 | G24: 47 | H24: =ROUND(H17+H23,2) -> 0 | I24: =ROUND(I17+I23,2) -> 0
B25: 固定资产原价 | C25: 18 | D25: 0 | E25: 0
B26: 减：累计折旧 | C26: 19 | D26: 0 | E26: 0
B27: 固定资产账面价值 | C27: 20 | D27: =ROUND(D25-D26,2) -> 0 | E27: =ROUND(E25-E26,2) -> 0
B28: 在建工程 | C28: 21 | D28: 0 | E28: 0
B29: 工程物资 | C29: 22 | D29: 0 | E29: 0
B30: 固定资产清理 | C30: 23 | D30: 0 | E30: 0
B31: 生物性生物资产 | C31: 24 | D31: 0 | E31: 0 | F31: 所有者权益（或股东权益）：
B32: 无形资产 | C32: 25 | D32: 0 | E32: 0 | F32: 实收资本（或股本） | G32: 48 | H32: 0 | I32: 0
B33: 开发支出 | C33: 26 | D33: 0 | E33: 0 | F33: 资本公积 | G33: 49 | H33: 0 | I33: 0
B34: 长期待摊费用 | C34: 27 | D34: 0 | E34: 0 | F34: 盈余公积 | G34: 50 | H34: 0 | I34: 0
B35: 其他非流动资产 | C35: 28 | D35: 0 | E35: 0 | F35: 未分配利润 | G35: 51 | H35: 0 | I35: 0
B36: 非流动资产合计 | C36: 29 | D36: =ROUND(D23+D24+D27+D28+D29+D30+D31+D32+D33+D34+D35,2) -> 0 | E36: =ROUND(E23+E24+E27+E28+E29+E30+E31+E32+E33+E34+E35,2) -> 0 | F36: 所有者权益（或股东权益）合计 | G36: 52 | H36: =ROUND(H32+H33+H34+H35,2) -> 0 | I36: =ROUND(I32+I33+I34+I35,2) -> 0
B37: 资产合计 | C37: 30 | D37: =ROUND(D21+D36,2) -> 0 | E37: =ROUND(E21+E36,2) -> 0 | F37: 负债和所有者权益（或股东权益）总计 | G37: 53 | H37: =ROUND(H24+H36,2) -> 0 | I37: =ROUND(I24+I36,2) -> 0

Sheet 利润表_月季报
B1: 利润表_月季报（适用执行小企业会计准则的企业）
F2: 会小企02表 单位：元
B3: 纳税人识别号 | D3: =IF(资产负债表!D3="","",资产负债表!D3) | E3: 纳税人名称 | F3: =IF(资产负债表!H3="","",资产负债表!H3)
B4: 所属期起 | D4: =IF(资产负债表!D4="","",资产负债表!D4) | E4: 所属期止 | F4: =IF(资产负债表!H4="","",资产负债表!H4)
B5: 项目 | C5: 行次 | D5: 本期金额 | E5: 本年累计金额
B6: 一、营业收入 | C6: 1 | D6: 0 | E6: 0
B7: 减：营业成本 | C7: 2 | D7: 0 | E7: 0
B8: 税金及附加 | C8: 3 | D8: 0 | E8: 0
B9: 其中：消费税 | C9: 4 | D9: 0 | E9: 0
B10: 营业税 | C10: 5 | D10: 0 | E10: 0
B11: 城市维护建设税 | C11: 6 | D11: 0 | E11: 0
B12: 资源税 | C12: 7 | D12: 0 | E12: 0
B13: 土地增值税 | C13: 8 | D13: 0 | E13: 0
B14: 城镇土地使用税、房产税、车船税、印花税 | C14: 9 | D14: 0 | E14: 0
B15: 教育费附加、矿产资源补偿费、排污费 | C15: 10 | D15: 0 | E15: 0
B16: 销售费用 | C16: 11 | D16: 0 | E16: 0
B17: 其中：商品维修费 | C17: 12 | D17: 0 | E17: 0
... B25: 加：投资收益（损失以“-”号填列） | C25: 20 | D25: 0 | E25: 0
B26: 二、营业利润（亏损以“-”号填列） | C26: 21 | D26: =ROUND(D6-D7-D8-D16-D19-D23+D25,2) -> 0 | E26: =ROUND(E6-E7-E8-E16-E19-E23+E25,2) -> 0
B27: 加：营业外收入 | C27: 22 | D27: 0 | E27: 0
B28: 其中：政府补助 | C28: 23 | D28: 0 | E28: 0
B29: 减：营业外支出 | C29: 24 | D29: 0 | E29: 0
B30: 其中：坏账损失 | C30: 25 | D30: 0 | E30: 0
B31: 无法收回的长期债券投资损失 | C31: 26 | D31: 0 | E31: 0
B32: 无法收回的长期股权投资损失 | C32: 27 | D32: 0 | E32: 0
B33: 自然灾害等不可抗力因素造成的损失 | C33: 28 | D33: 0 | E33: 0
B34: 税收滞纳金 | C34: 29 | D34: 0 | E34: 0
B35: 三、利润总额（亏损总额以“-”号填列） | C35: 30 | D35: =ROUND(D26+D27-D29,2) -> 0 | E35: =ROUND(E26+E27-E29,2) -> 0
B36: 减：所得税费用 | C36: 31 | D36: 0 | E36: 0
B37: 四、净利润（净亏损以“-”号填列） | C37: 32 | D37: =ROUND(D35-D36,2) -> 0 | E37: =ROUND(E35-E36,2) -> 0

Sheet 现金流量表_月季报
B1: 现金流量表_月季报（适用执行小企业会计准则的企业）
F2: 会小企03表 单位：元
B3: 纳税人识别号 | D3: =IF(资产负债表!D3="","",资产负债表!D3) | E3: 纳税人名称 | F3: =IF(资产负债表!H3="","",资产负债表!H3)
B4: 所属期起 | D4: =IF(资产负债表!D4="","",资产负债表!D4) | E4: 所属期止 | F4: =IF(资产负债表!H4="","",资产负债表!H4)
B5: 项目 | C5: 行次 | D5: 本期金额 | E5: 本年累计金额
B6: 一、经营活动生产的现金流量：
B7: 销售产成品、商品、提供劳务收到的现金 | C7: 1 | D7: 0 | E7: 0
B8: 收到其他与经营活动有关的现金 | C8: 2 | D8: 0 | E8: 0
B9: 购买原材料、商品、接受劳务支付的现金 | C9: 3 | D9: 0 | E9: 0
B10: 支付的职工薪酬 | C10: 4 | D10: 0 | E10: 0
B11: 支付的税费 | C11: 5 | D11: 0 | E11: 0
B12: 支付其他与经营活动有关的现金 | C12: 6 | D12: 0 | E12: 0
B13: 经营活动产生的现金流量净额 | C13: 7 | D13: =ROUND(D7+D8-D9-D10-D11-D12,2) -> 0 | E13: =ROUND(E7+E8-E9-E10-E11-E12,2) -> 0
B14: 二、投资活动产生的现金流量：
B15: 收回短期投资、长期债券投资和长期股权投资收到的现金 | C15: 8 | D15: 0 | E15: 0
B16: 取得投资收益收到的现金 | C16: 9 | D16: 0 | E16: 0
B17: 处置固定资产、无形资产和其他非流动资产收回的现金净额 | C17: 10 | D17: 0 | E17: 0
B18: 短期投资、长期债券投资和长期股权投资支付的现金 | C18: 11 | D18: 0 | E18: 0
B19: 购建固定资产、无形资产和其他非流动资产支付的现金 | C19: 12 | D19: 0 | E19: 0
B20: 投资活动产生的现金流量净额 | C20: 13 | D20: =ROUND(D15+D16+D17-D18-D19,2) -> 0 | E20: =ROUND(E15+E16+E17-E18-E19,2) -> 0
B21: 三、筹资活动产生的现金流量：
B22: 取得借款收到的现金 | C22: 14 | D22: 0 | E22: 0
B23: 吸收投资者投资收到的现金 | C23: 15 | D23: 0 | E23: 0
B24: 偿还借款本金支付的现金 | C24: 16 | D24: 0 | E24: 0
B25: 偿还借款利息支付的现金 | C25: 17 | D25: 0 | E25: 0
B26: 分配利润支付的现金 | C26: 18 | D26: 0 | E26: 0
B27: 筹资活动产生的现金流量净额 | C27: 19 | D27: =ROUND(D22+D23-D24-D25-D26,2) -> 0 | E27: =ROUND(E22+E23-E24-E25-E26,2) -> 0
B28: 四、现金净增加额 | C28: 20 | D28: =ROUND(D13+D20+D27,2) -> 0 | E28: =ROUND(E13+E20+E27,2) -> 0
B29: 加：期初现金余额 | C29: 21 | D29: 0 | E29: 0
B30: 五、期末现金余额 | C30: 22 | D30: =ROUND(D28+D29,2) -> 0 | E30: =ROUND(E28+E29,2) -> 0
